{
  "transactions": [
    {
      "id": 1,
      "description": "Desenvolvimento de site",
      "type": "income",
      "category": "Venda",
      "price": 14000,
      "createdAt": "2022-12-01T23:31:28.116Z"
    },
    {
      "id": 2,
      "description": "Hamburger",
      "type": "outcome",
      "category": "Alimentação",
      "price": 50,
      "createdAt": "2022-12-01T23:31:55.116Z"
    },
    {
      "id": 3,
      "description": "Computer Science",
      "type": "outcome",
      "category": "Educação",
      "price": 1550,
      "createdAt": "2022-12-01T23:31:55.116Z"
    },
    {
      "category": "DDDDDDDD",
      "type": "income",
      "price": 909,
      "description": "~]kllç~l~k",
      "createdAt": "2022-12-03T17:55:17.652Z",
      "id": 4
    }
  ]
}